zevon/__init__.py
zevon/flask_lambda.py
zevon/sample_event.py
zevon/welcome.py
Zevon-0.5.0.dist-info/LICENSE
Zevon-0.5.0.dist-info/METADATA
Zevon-0.5.0.dist-info/WHEEL
Zevon-0.5.0.dist-info/top_level.txt
Zevon-0.5.0.dist-info/RECORD
